joyit_wlgamepad-1.0.1.dist-info/licenses/LICENSE
wlgamepad/__init__.py
wlgamepad/wlgamepad.py
joyit_wlgamepad-1.0.1.dist-info/METADATA
joyit_wlgamepad-1.0.1.dist-info/WHEEL
joyit_wlgamepad-1.0.1.dist-info/top_level.txt
joyit_wlgamepad-1.0.1.dist-info/RECORD
