Metadata-Version: 2.4
Name: JoyIT_WLGamepad
Version: 1.0.1
Summary: Library to use the SBC-WLGamepad with the Raspberry Pi
Home-page: https://github.com/joy-it/JoyIT_WLGamepad
Author: Joy-IT
Author-email: Joy-IT <service@joy-it.net>
Project-URL: Homepage, https://github.com/joy-it/JoyIT_WLGamepad
Project-URL: Issues, https://github.com/joy-it/JoyIT_WLGamepad/issues
Classifier: Programming Language :: Python :: 3
Classifier: Operating System :: OS Independent
Requires-Python: >=3.7
License-File: LICENSE
Requires-Dist: lgpio
Dynamic: author
Dynamic: home-page
Dynamic: license-file
Dynamic: requires-python
